Workbook

Sheet Fertilizante
A1: PRODUTO | C1: DOSE/HÁ | D1: PREÇO | E1: Embalagem
A2: 00-19-00 | B2: FERTILIZANTE | C2: 200 | D2: 320 | E2: 1
A3: 00-32-00 | B3: FERTILIZANTE | C3: 0 | D3: 400 | E3: 1
A4: 02-20-20 | B4: FERTILIZANTE | C4: 0 | D4: 425 | E4: 1
A5: 04-30-10 | B5: FERTILIZANTE | C5: 0 | D5: 435 | E5: 1
A6: 05-25-25 | B6: FERTILIZANTE | C6: 0 | D6: 480 | E6: 1
A7: 06-30-06 | B7: FERTILIZANTE | C7: 0 | D7: 430 | E7: 1
A8: 08-20-10 | B8: FERTILIZANTE | C8: 0 | D8: 420 | E8: 1
A9: KCL | B9: FERTILIZANTE | C9: 0.1 | D9: 460 | E9: 1

Sheet Sementes
A1: SEM SOJA 63I64RSF IPRO S/T - (5,5) | B1: SEMENTE | D1: 1.2633687 | E1: 25
A2: SEM SOJA 63I64RSF IPRO S/T - (6,5) | B2: SEMENTE | D2: 1.0030382 | E2: 25
A3: SEM SOJA 63I64RSF IPRO + TSI + INOCULANTE - (5,5) | B3: SEMENTE | D3: 1.94 | E3: 25
A4: SEM SOJA 63I64RSF IPRO + TSI + INOCULANTE - (6,5) | B4: SEMENTE | D4: 1.66 | E4: 25
A5: SEM SOJA BS 2606 S/T - (5,5) | B5: SEMENTE | D5: 1.2 | E5: 25
A6: SEM SOJA BS 2606 S/T - (6,5) | B6: SEMENTE | D6: 0.91115685 | E6: 25
A7: SEM SOJA BS 2606 TSI + TSI + INOCULANTE - (5,5) | B7: SEMENTE | D7: 1.75 | E7: 25
A8: SEM SOJA BS 2606 TSI + TSI + INOCULANTE - (6,5) | B8: SEMENTE | D8: 1.5236993 | E8: 25
A9: SEM SOJA M5947IPRO S/T - (5,5) | B9: SEMENTE | C9: 0 | D9: 1.1714874 | E9: 25
A10: SEM SOJA M5947IPRO S/T - (6,5) | B10: SEMENTE | C10: 0 | D10: 0.91115685 | E10: 25
A11: SEM SOJA M5947IPRO TSI + ECOTRICH - (5,5) | B11: SEMENTE | C11: 40 | D11: 1.89 | E11: 25
A12: SEM SOJA M5947IPRO TSI + ECOTRICH - (6,5) | B12: SEMENTE | C12: 0 | D12: 1.66 | E12: 25
A13: SEM SOJA M6210IPRO + TSI+ INOCULANTE - (5,5) | B13: SEMENTE | C13: 0 | D13: 1.81 | E13: 25
A14: SEM SOJA M6210IPRO + TSI+ INOCULANTE - (6,5) | B14: SEMENTE | C14: 0 | D14: 1.56 | E14: 25
A15: SEM SOJA M6210IPRO S/T - (5,5) | B15: SEMENTE | C15: 0 | D15: 1.1408603 | E15: 25
A16: SEM SOJA M6210IPRO S/T - (6,5) | B16: SEMENTE | C16: 0 | D16: 0.91115685 | E16: 25
A17: SEM SOJA M6410 + TSI + INOCULANTE - (5,5) | B17: SEMENTE | C17: 0 | D17: 1.82 | E17: 25
A18: SEM SOJA M6410 + TSI + INOCULANTE - (6,5) | B18: SEMENTE | C18: 0 | D18: 1.57 | E18: 25
A19: SEM SOJA M6410 S/T - (5,5) | B19: SEMENTE | C19: 0 | D19: 1.1714874 | E19: 25
A20: SEM SOJA M6410 S/T - (6,5) | B20: SEMENTE | C20: 0 | D20: 0.94178397 | E20: 25
A21: SEM SOJA NA5909 + TSI + INOCULANTE - (5,5) | B21: SEMENTE | D21: 2.04 | E21: 25
A22: SEM SOJA NA5909 + TSI + INOCULANTE - (6,5) | B22: SEMENTE | D22: 1.82 | E22: 25
A23: SEM SOJA NA5909 S/T - (5,5) | B23: SEMENTE | D23: 1.3512686 | E23: 25
A24: SEM SOJA NA5909 S/T - (6,5) | B24: SEMENTE | D24: 1.1521923 | E24: 25
A25: SEM SOJA TMG 7062 IPRO + TSI +INOCULANTE - (5,5) | B25: SEMENTE | C25: 0 | D25: 2.09 | E25: 25
A26: SEM SOJA TMG 7062 IPRO + TSI +INOCULANTE - (6,5) | B26: SEMENTE | C26: 0 | D26: 1.76 | E26: 25
A27: SEM SOJA TMG 7062 IPRO S/T - (5,5) | B27: SEMENTE | C27: 0 | D27: 1.4014358 | E27: 25
A28: SEM SOJA TMG 7062 IPRO S/T - (6,5) | B28: SEMENTE | C28: 0 | D28: 1.0951646 | E28: 25
A29: SEM SOJA TMG 7262RR + TSI + INOCULANTE - (5,5) | B29: SEMENTE | D29: 2.09 | E29: 25
A30: SEM SOJA TMG 7262RR + TSI + INOCULANTE - (6,5) | B30: SEMENTE | D30: 1.8 | E30: 25
A31: SEM SOJA TMG 7262RR S/T - (5,5) | B31: SEMENTE | D31: 1.4167494 | E31: 25
A32: SEM SOJA TMG 7262RR S/T - (6,5) | B32: SEMENTE | D32: 1.0951646 | E32: 25
A33: SEM SOJA TMG7063IPRO + TSI + INOCULANTE - (5,5) | B33: SEMENTE | D33: 2.14 | E33: 25
A34: SEM SOJA TMG7063IPRO + TSI + INOCULANTE - (6,5) | B34: SEMENTE | D34: 1.77 | E34: 25
A35: SEM SOJA TMG7063IPRO S/T - (5,5) | B35: SEMENTE | D35: 1.4473765 | E35: 25
A36: SEM SOJA TMG7063IPRO S/T - (6,5) | B36: SEMENTE | D36: 1.11 | E36: 25

Sheet Precos
B1: Produtos | C1: Pricipio Ativo | D1: Precio | E1: Embalagem | F1: Custo | G1: Margem | H1: Precio Real | I1: Margem Real | J1: DIF
B2: Fert. 00-00-60 Fertipar C | E2: 1000 | G2: =(D2-F2)/F2 -> #DIV/0! | H2: 0.495 | I2: =(H2-F2)/F2 -> #DIV/0! | J2: =G2-I2 -> #DIV/0! | K2: 0.0018 | L2: =G2-19% -> #DIV/0!
B3: Fert. 02-23-23 TopMix Evo. Yara C | E3: 1000 | G3: =(D3-F3)/F3 -> #DIV/0! | H3: 0.685 | I3: =(H3-F3)/F3 -> #DIV/0! | J3: =G3-I3 -> #DIV/0! | K3: 0.0018 | L3: =G3-19% -> #DIV/0!
B4: Fert. 08-40-08 TopMIx Evo. Yara C | E4: 1000 | G4: =(D4-F4)/F4 -> #DIV/0! | H4: 0.883 | I4: =(H4-F4)/F4 -> #DIV/0! | J4: =G4-I4 -> #DIV/0! | K4: 0.002 | L4: =G4-19% -> #DIV/0!
L5: =G5-19% -> -0.19
B6: 55I57 RSF IPRO (ZEUS) (260mil/Ha) + TSIA | C6: Sem Soja | D6: 63 | E6: 1 | F6: 45.57 | G6: =(D6-F6)/F6 -> 0.38248848 | H6: 50 | I6: =(H6-F6)/F6 -> 0.097213079 | J6: =G6-I6 -> 0.2852754 | K6: 0.025 | L6: =G6-19% -> 0.19248848
B7: 55I57 RSF IPRO (ZEUS) (260mil/Ha) A | C7: Sem Soja | D7: 42 | E7: 1 | F7: 31.89 | G7: =(D7-F7)/F7 -> 0.31702728 | H7: 29.308859 | I7: =(H7-F7)/F7 -> -0.080938898 | J7: =G7-I7 -> 0.39796618 | K7: 0.025 | L7: =G7-19% -> 0.12702728
B8: 63IX65 RSF (COLISEU) (235mil/Há) + TSI A | C8: Sem Soja | D8: 48 | E8: 1 | F8: 34.75 | G8: =(D8-F8)/F8 -> 0.38129496 | I8: =(H8-F8)/F8 -> -1 | J8: =G8-I8 -> 1.381295 | K8: 0.025 | L8: =G8-19% -> 0.19129496
B9: 63IX65 RSF (COLISEU) (235mil/Há) A | C9: Sem Soja | D9: 33.8 | E9: 1 | F9: 24.33 | G9: =(D9-F9)/F9 -> 0.3892314 | H9: 26 | I9: =(H9-F9)/F9 -> 0.06863954 | J9: =G9-I9 -> 0.32059186 | K9: 0.025 | L9: =G9-19% -> 0.1992314
B10: 64I61 RSF IPRO (FIBRA) (235mil/Ha) + TSI A | C10: Sem Soja | D10: 47.5 | E10: 1 | F10: 34.16 | G10: =(D10-F10)/F10 -> 0.39051522 | I10: =(H10-F10)/F10 -> -1 | J10: =G10-I10 -> 1.3905152 | K10: 0.025 | L10: =G10-19% -> 0.20051522
B11: 64I61 RSF IPRO (FIBRA) (235mil/Ha) A | C11: Sem Soja | D11: 33 | E11: 1 | F11: 23.92 | G11: =(D11-F11)/F11 -> 0.37959866 | H11: 25.44899 | I11: =(H11-F11)/F11 -> 0.063920985 | J11: =G11-I11 -> 0.31567768 | K11: 0.025 | L11: =G11-19% -> 0.18959866
B12: 64IX66 RSF (NEXUS) (235mil/Há) + TSI A | C12: Sem Soja | D12: 47.5 | E12: 1 | F12: 34.01 | G12: =(D12-F12)/F12 -> 0.39664804 | I12: =(H12-F12)/F12 -> -1 | J12: =G12-I12 -> 1.396648 | K12: 0.025 | L12: =G12-19% -> 0.20664804
B13: 64IX66 RSF (NEXUS) (235mil/Há) A | C13: Sem Soja | D13: 33 | E13: 1 | F13: 23.81 | G13: =(D13-F13)/F13 -> 0.38597228 | H13: 26 | I13: =(H13-F13)/F13 -> 0.09197816 | J13: =G13-I13 -> 0.29399412 | K13: 0.025 | L13: =G13-19% -> 0.19597228
B14: 65I65 RSF IPRO (COMPACTA) (240mil/Ha) + TSI A | C14: Sem Soja | D14: 55.5 | E14: 1 | F14: 39.9 | G14: =(D14-F14)/F14 -> 0.39097744 | I14: =(H14-F14)/F14 -> -1 | J14: =G14-I14 -> 1.3909774 | K14: 0.025 | L14: =G14-19% -> 0.20097744
B15: 65I65 RSF IPRO (COMPACTA) (240mil/Ha) A | C15: Sem Soja | D15: 39 | E15: 1 | F15: 27.93 | G15: =(D15-F15)/F15 -> 0.39634801 | H15: 30.568693 | I15: =(H15-F15)/F15 -> 0.094475229 | J15: =G15-I15 -> 0.30187278 | K15: 0.025 | L15: =G15-19% -> 0.20634801
B16: DM66I68 RSF IPRO (230mil/Há + TSI A | C16: Sem Soja | D16: 59 | E16: 1 | F16: 42.49 | G16: =(D16-F16)/F16 -> 0.38856201 | I16: =(H16-F16)/F16 -> -1 | J16: =G16-I16 -> 1.388562 | K16: 0.025 | L16: =G16-19% -> 0.19856201
B17: DM66I68 RSF IPRO (230mil/Há A | C17: Sem Soja | D17: 41 | E17: 1 | F17: 29.74 | G17: =(D17-F17)/F17 -> 0.37861466 | H17: 40.018635 | I17: =(H17-F17)/F17 -> 0.3456165 | J17: =G17-I17 -> 0.032998162 | K17: 0.025 | L17: =G17-19% -> 0.18861466
B18: M5921 I2X (240mil/Ha) + TSI A | C18: Sem Soja | D18: 48.5 | E18: 1 | F18: 34.92 | G18: =(D18-F18)/F18 -> 0.38888889 | I18: =(H18-F18)/F18 -> -1 | J18: =G18-I18 -> 1.3888889 | K18: 0.025 | L18: =G18-19% -> 0.19888889
B19: M5921 I2X (240mil/Ha) A | C19: Sem Soja | D19: 34 | E19: 1 | F19: 24.44 | G19: =(D19-F19)/F19 -> 0.39116203 | H19: 28.878671 | I19: =(H19-F19)/F19 -> 0.18161502 | J19: =G19-I19 -> 0.20954701 | K19: 0.025 | L19: =G19-19% -> 0.20116203
B20: M5947 IPRO (240mil/Ha) + TSI A | C20: Sem Soja | D20: 46.8 | E20: 1 | F20: 33.48 | G20: =(D20-F20)/F20 -> 0.39784946 | I20: =(H20-F20)/F20 -> -1 | J20: =G20-I20 -> 1.3978495 | K20: 0.025 | L20: =G20-19% -> 0.20784946
B21: M5947 IPRO (240mil/Ha) A | C21: Sem Soja | D21: 33 | E21: 1 | F21: 23.44 | G21: =(D21-F21)/F21 -> 0.40784983 | H21: 26.942828 | I21: =(H21-F21)/F21 -> 0.14943804 | J21: =G21-I21 -> 0.25841179 | K21: 0.025 | L21: =G21-19% -> 0.21784983
B22: M6130 I2X (230mil/Ha) + TSI A | C22: Sem Soja | D22: 50 | E22: 1 | F22: 36.78 | G22: =(D22-F22)/F22 -> 0.35943448 | I22: =(H22-F22)/F22 -> -1 | J22: =G22-I22 -> 1.3594345 | K22: 0.025 | L22: =G22-19% -> 0.16943448
B23: M6130 I2X (230mil/Ha) A | C23: Sem Soja | D23: 35.5 | E23: 1 | F23: 25.75 | G23: =(D23-F23)/F23 -> 0.37864078 | H23: 25.895723 | I23: =(H23-F23)/F23 -> 0.0056591486 | J23: =G23-I23 -> 0.37298163 | K23: 0.025 | L23: =G23-19% -> 0.18864078
B25: Acrescent Raiz F (2ml/Kg) A | D25: 99 | E25: 5 | F25: 70 | G25: =(D25-F25)/F25 -> 0.41428571 | H25: 99.52 | I25: =(H25-F25)/F25 -> 0.42171429 | J25: =G25-I25 -> -0.0074285714 | K25: 0.04 | L25: =G25-19% -> 0.22428571
B26: Clorante 62,5 (0,5 ml/Kg) A | D26: 90 | E26: 5 | F26: 60 | G26: =(D26-F26)/F26 -> 0.5 | H26: 33 | I26: =(H26-F26)/F26 -> -0.45 | J26: =G26-I26 -> 0.95 | K26: 0.01 | L26: =G26-19% -> 0.31
B27: Dermacor (0,5ml/Kg) C | D27: 198 | E27: 5 | F27: 165 | G27: =(D27-F27)/F27 -> 0.2 | J27: =G27-I27 -> 0.2 | K27: 0.004 | L27: =G27-19% -> 0.01
B28: Ever Gold (0,9ml/Kg) C | D28: 66 | E28: 5 | F28: 53 | G28: =(D28-F28)/F28 -> 0.24528302 | J28: =G28-I28 -> 0.24528302 | K28: 0.004 | L28: =G28-19% -> 0.055283019
B29: Fertactyl Leg (2 ml/kg) A | D29: 107 | E29: 2 | F29: 79 | G29: =(D29-F29)/F29 -> 0.35443038 | H29: 94.53 | I29: =(H29-F29)/F29 -> 0.19658228 | J29: =G29-I29 -> 0.1578481 | K29: 0.04 | L29: =G29-19% -> 0.16443038
B30: Rancona (1 ml/kg) C | C30: Metalaxil 2% + Fludioxonil 2,5% + Tiabendazol 15% | D30: 49.5 | E30: 1 | F30: 42 | G30: =(D30-F30)/F30 -> 0.17857143 | H30: 47 | I30: =(H30-F30)/F30 -> 0.11904762 | J30: =G30-I30 -> 0.05952381 | K30: 0.004 | L30: =G30-19% -> -0.011428571
B31: Rizoderma Max (2 ml/kg + 1 ml/kg) B | C31: Trichoderma harzianum 2 (Th2) Bj Rizoderma de 9lts cada + Protector de 3 L cada. Para 3000 kg de semilla | D31: 66 | E31: 2 | F31: 47.5 | G31: =(D31-F31)/F31 -> 0.38947368 | H31: 58 | I31: =(H31-F31)/F31 -> 0.22105263 | J31: =G31-I31 -> 0.16842105 | K31: 0.04 | L31: =G31-19% -> 0.19947368
B32: Rizoliq Top (2 ml/kg) A | C32: Inoculante soja 2X10a10’ | D32: 26 | E32: 2 | F32: 16 | G32: =(D32-F32)/F32 -> 0.625 | H32: 21 | I32: =(H32-F32)/F32 -> 0.3125 | J32: =G32-I32 -> 0.3125 | K32: 0.04 | L32: =G32-19% -> 0.435
B33: VitaGrow TS (1ml/Kg) A | D33: 72 | E33: 5 | F33: 47 | G33: =(D33-F33)/F33 -> 0.53191489 | H33: 68 | I33: =(H33-F33)/F33 -> 0.44680851 | J33: =G33-I33 -> 0.085106383 | K33: 0.04 | L33: =G33-19% -> 0.34191489
B34: Rizospirilum (2ml/Kg) A | D34: 40 | E34: 2 | F34: 25 | G34: =(D34-F34)/F34 -> 0.6 | H34: 30 | I34: =(H34-F34)/F34 -> 0.2 | J34: =G34-I34 -> 0.4 | K34: 0.04 | L34: =G34-19% -> 0.41
B36: Clomazone 48% (0,8 - 1) C | D36: 9.5 | E36: 5 | F36: 7.5 | G36: =(D36-F36)/F36 -> 0.26666667 | H36: 8.5 | K36: 0.004 | L36: =G36-19% -> 0.076666667
B37: Flumioxazin 48% (0,1) B | C37: Flumioxazin 48% | D37: 34 | E37: 5 | F37: 26 | G37: =(D37-F37)/F37 -> 0.30769231 | H37: 35 | I37: =(H37-F37)/F37 -> 0.34615385 | J37: =G37-I37 -> -0.038461538 | K37: 0.007 | L37: =G37-19% -> 0.11769231
B38: Glufosinato 40 (1,5 – 2,5) C | C38: Glufosinato 40% | D38: 6.1 | E38: 20 | F38: 4.9 | G38: =(D38-F38)/F38 -> 0.24489796 | H38: 9 | I38: =(H38-F38)/F38 -> 0.83673469 | J38: =G38-I38 -> -0.59183673 | K38: 0.004 | L38: =G38-19% -> 0.054897959
B39: Pixxaro (0,3 - 0,4) C | D39: 68.5 | E39: 5 | F39: 57 | G39: =(D39-F39)/F39 -> 0.20175439 | H39: 62 | I39: =(H39-F39)/F39 -> 0.087719298 | J39: =G39-I39 -> 0.11403509 | K39: 0.004 | L39: =G39-19% -> 0.011754386
B40: Saflunex 70 (0,8) C | D40: 220 | E40: 0.35 | F40: 180 | G40: =(D40-F40)/F40 -> 0.22222222 | L40: =G40-19% -> 0.032222222
B41: Strim (1-1,5) B | C41: S-metalacloro 96% | D41: 14 | E41: 20 | F41: 10 | G41: =(D41-F41)/F41 -> 0.4 | H41: 11.5 | I41: =(H41-F41)/F41 -> 0.15 | J41: =G41-I41 -> 0.25 | K41: 0.007 | L41: =G41-19% -> 0.21
B42: Texaro (0,043) C | D42: 546 | E42: 0.86 | F42: 465 | G42: =(D42-F42)/F42 -> 0.17419355 | H42: 520 | I42: =(H42-F42)/F42 -> 0.11827957 | J42: =G42-I42 -> 0.055913978 | K42: 0.004 | L42: =G42-19% -> -0.015806452
B43: Verdict Ultra (0,08) C | D43: 88 | E43: 5 | F43: 72 | G43: =(D43-F43)/F43 -> 0.22222222 | H43: 76 | I43: =(H43-F43)/F43 -> 0.055555556 | J43: =G43-I43 -> 0.16666667 | K43: 0.004 | L43: =G43-19% -> 0.032222222
B45: Alsystin (0,05) A | C45: Triflumuron 25% | D45: 57 | E45: 1 | F45: 43.73 | G45: =(D45-F45)/F45 -> 0.30345301 | H45: 48 | I45: =(H45-F45)/F45 -> 0.097644638 | J45: =G45-I45 -> 0.20580837 | K45: 0.01 | L45: =G45-19% -> 0.11345301
B46: Bulldock (250 ML) (0,05) C | C46: Betaciflutrina 12,5% | D46: 52 | E46: 0.25 | F46: 41.76 | G46: =(D46-F46)/F46 -> 0.24521073 | H46: 47 | I46: =(H46-F46)/F46 -> 0.12547893 | J46: =G46-I46 -> 0.1197318 | K46: 0.004 | L46: =G46-19% -> 0.055210728
B47: Clorante 80% (0,04) C | C47: Clorantraniliproli 62,5% | D47: 90 | E47: 1 | F47: 70 | G47: =(D47-F47)/F47 -> 0.28571429 | H47: 98 | I47: =(H47-F47)/F47 -> 0.4 | J47: =G47-I47 -> -0.11428571 | K47: 0.004 | L47: =G47-19% -> 0.095714286
B48: Expedition (0,5) C | D48: 44 | E48: 5 | F48: 36 | G48: =(D48-F48)/F48 -> 0.22222222 | H48: 40 | I48: =(H48-F48)/F48 -> 0.11111111 | J48: =G48-I48 -> 0.11111111 | K48: 0.004 | L48: =G48-19% -> 0.032222222
B49: Intrepid (0,3) A | D49: 33 | E49: 5 | F49: 24.5 | G49: =(D49-F49)/F49 -> 0.34693878 | H49: 27.5 | I49: =(H49-F49)/F49 -> 0.12244898 | J49: =G49-I49 -> 0.2244898 | K49: 0.01 | L49: =G49-19% -> 0.15693878
B50: Ippon (0,15) B | D50: 17 | E50: 5 | F50: 13 | G50: =(D50-F50)/F50 -> 0.30769231 | H50: 15.5 | I50: =(H50-F50)/F50 -> 0.19230769 | J50: =G50-I50 -> 0.11538462 | K50: 0.007 | L50: =G50-19% -> 0.11769231
B51: Lascar (0,8 – 1,0) B | C51: Acefato 97% | D51: 11.8 | E51: 5 | F51: 9 | G51: =(D51-F51)/F51 -> 0.31111111 | H51: 12 | I51: =(H51-F51)/F51 -> 0.33333333 | J51: =G51-I51 -> -0.022222222 | K51: 0.007 | L51: =G51-19% -> 0.12111111
B52: Loyer (0,4 - 0,5) A | D52: 19.8 | E52: 5 | F52: 14.5 | G52: =(D52-F52)/F52 -> 0.36551724 | H52: 18 | I52: =(H52-F52)/F52 -> 0.24137931 | J52: =G52-I52 -> 0.12413793 | K52: 0.01 | L52: =G52-19% -> 0.17551724
B53: Quintal Xtra (0,2) A | D53: 111 | E53: 5 | F53: 92 | G53: =(D53-F53)/F53 -> 0.20652174 | H53: 100 | I53: =(H53-F53)/F53 -> 0.086956522 | J53: =G53-I53 -> 0.11956522 | K53: 0.01 | L53: =G53-19% -> 0.016521739
B54: Solomon (0,4) C | D54: 35 | E54: 5 | F54: 27.85 | G54: =(D54-F54)/F54 -> 0.2567325 | H54: 30 | I54: =(H54-F54)/F54 -> 0.077199282 | J54: =G54-I54 -> 0.17953321 | K54: 0.004 | L54: =G54-19% -> 0.066732496
B55: Soyguard (0,08 – 0,1) B | C55: Teflubenzuron 30% | D55: 37 | E55: 1 | F55: 30 | G55: =(D55-F55)/F55 -> 0.23333333 | H55: 36 | I55: =(H55-F55)/F55 -> 0.2 | J55: =G55-I55 -> 0.033333333 | K55: 0.007 | L55: =G55-19% -> 0.043333333
B56: Toxatrin (0,3 - 0,5) A | D56: 19.5 | E56: 5 | F56: 12.5 | G56: =(D56-F56)/F56 -> 0.56 | H56: 15.5 | I56: =(H56-F56)/F56 -> 0.24 | J56: =G56-I56 -> 0.32 | K56: 0.01 | L56: =G56-19% -> 0.37
B58: Aproach Power (0,6) C | D58: 28 | E58: 5 | F58: 23 | G58: =(D58-F58)/F58 -> 0.2173913 | H58: 26 | I58: =(H58-F58)/F58 -> 0.13043478 | J58: =G58-I58 -> 0.086956522 | K58: 0.004 | L58: =G58-19% -> 0.027391304
B59: Cripton XPRO (0,5) C | C59: Trifloxistrobin 15% + Prothioconazole 17,5% + Bixafen 12,5% | D59: 64 | E59: 5 | F59: 56 | G59: =(D59-F59)/F59 -> 0.14285714 | H59: 62.85 | I59: =(H59-F59)/F59 -> 0.12232143 | J59: =G59-I59 -> 0.020535714 | K59: 0.004 | L59: =G59-19% -> -0.047142857
B60: Difenazol (0,5) A | C60: Difeno 20% + Tebuco 20% | D60: 17.5 | E60: 5 | F60: 8.5 | G60: =(D60-F60)/F60 -> 1.0588235 | H60: 12 | I60: =(H60-F60)/F60 -> 0.41176471 | J60: =G60-I60 -> 0.64705882 | K60: 0.01 | L60: =G60-19% -> 0.86882353
B61: Muralla (1,5 – 3,0) C | C61: Mancozeb 75% WG | D61: 5.9 | E61: 15 | F61: 4.85 | G61: =(D61-F61)/F61 -> 0.21649485 | H61: 5.5 | I61: =(H61-F61)/F61 -> 0.13402062 | J61: =G61-I61 -> 0.082474227 | K61: 0.004 | L61: =G61-19% -> 0.026494845
B62: Nativo (0,5) C | C62: Trifloxistrobin 10% + Tebuconazole 20% | D62: 23.8 | E62: 5 | F62: 19.8 | G62: =(D62-F62)/F62 -> 0.2020202 | H62: 21.5 | I62: =(H62-F62)/F62 -> 0.085858586 | J62: =G62-I62 -> 0.11616162 | K62: 0.004 | L62: =G62-19% -> 0.012020202
B63: Sphere Max (0,2) C | C63: Trifloxistrobina 37,5% + Ciproconazol 16% | D63: 76 | E63: 5 | F63: 62 | G63: =(D63-F63)/F63 -> 0.22580645 | H63: 74 | I63: =(H63-F63)/F63 -> 0.19354839 | J63: =G63-I63 -> 0.032258065 | K63: 0.004 | L63: =G63-19% -> 0.035806452
B64: Tampronil 72% (1,5) A | C64: Clorotalonil 72% | D64: 5.8 | E64: 20 | F64: 4.3 | G64: =(D64-F64)/F64 -> 0.34883721 | H64: 5 | I64: =(H64-F64)/F64 -> 0.1627907 | J64: =G64-I64 -> 0.18604651 | K64: 0.01 | L64: =G64-19% -> 0.15883721
B65: Vessaria (0,6) B | D65: 42.5 | E65: 10 | F65: 36.5 | G65: =(D65-F65)/F65 -> 0.16438356 | H65: 40 | I65: =(H65-F65)/F65 -> 0.095890411 | J65: =G65-I65 -> 0.068493151 | K65: 0.007 | L65: =G65-19% -> -0.025616438
B66: Viovan (0,6) B | C66: Picoxis + Protio | D66: 40 | E66: 10 | F66: 31 | G66: =(D66-F66)/F66 -> 0.29032258 | H66: 37 | I66: =(H66-F66)/F66 -> 0.19354839 | J66: =G66-I66 -> 0.096774194 | K66: 0.007 | L66: =G66-19% -> 0.10032258
B68: Acrescent sollus F (2) A | D68: 11.5 | E68: 25 | F68: 7 | G68: =(D68-F68)/F68 -> 0.64285714 | H68: 8.47 | I68: =(H68-F68)/F68 -> 0.21 | J68: =G68-I68 -> 0.43285714 | K68: 0.04 | L68: =G68-19% -> 0.45285714
B69: Fertactyl GZ (0,5) A | D69: 31.8 | E69: 10 | F69: 22.5 | G69: =(D69-F69)/F69 -> 0.41333333 | H69: 28 | I69: =(H69-F69)/F69 -> 0.24444444 | J69: =G69-I69 -> 0.16888889 | K69: 0.04 | L69: =G69-19% -> 0.22333333
B70: Fertileader Vital 954 (1) A | D70: 28.85 | E70: 10 | F70: 19.5 | G70: =(D70-F70)/F70 -> 0.47948718 | H70: 25 | I70: =(H70-F70)/F70 -> 0.28205128 | J70: =G70-I70 -> 0.1974359 | K70: 0.04 | L70: =G70-19% -> 0.28948718
B71: Optimizer (0,2 – 0,3) A | C71: Aceite Vegetal | D71: 8 | E71: 5 | F71: 5.5 | G71: =(D71-F71)/F71 -> 0.45454545 | H71: 6.5 | I71: =(H71-F71)/F71 -> 0.18181818 | J71: =G71-I71 -> 0.27272727 | K71: 0.04 | L71: =G71-19% -> 0.26454545
B72: Progen Detox (0,4) A | D72: 31.85 | E72: 10 | F72: 22.8 | G72: =(D72-F72)/F72 -> 0.39692982 | H72: 27 | I72: =(H72-F72)/F72 -> 0.18421053 | J72: =G72-I72 -> 0.2127193 | K72: 0.04 | L72: =G72-19% -> 0.20692982
B73: Rizoil M (0,2) A | D73: 6 | E73: 10 | F73: 4.4 | G73: =(D73-F73)/F73 -> 0.36363636 | H73: 5 | I73: =(H73-F73)/F73 -> 0.13636364 | J73: =G73-I73 -> 0.22727273 | K73: 0.04 | L73: =G73-19% -> 0.17363636
B74: Sticker Oil (0,2 - 0,5) A | D74: 4.3 | E74: 20 | F74: 2.4 | G74: =(D74-F74)/F74 -> 0.79166667 | H74: 2.7 | I74: =(H74-F74)/F74 -> 0.125 | J74: =G74-I74 -> 0.66666667 | K74: 0.04 | L74: =G74-19% -> 0.60166667
B75: TA35 5 L (0,05) A | D75: 26 | E75: 5 | F75: 16.5 | G75: =(D75-F75)/F75 -> 0.57575758 | H75: 29.5 | I75: =(H75-F75)/F75 -> 0.78787879 | J75: =G75-I75 -> -0.21212121 | K75: 0.04 | L75: =G75-19% -> 0.38575758
B76: U10 (0,05) A | D76: 26 | E76: 1 | F76: 16.5 | G76: =(D76-F76)/F76 -> 0.57575758 | H76: 29.5 | I76: =(H76-F76)/F76 -> 0.78787879 | J76: =G76-I76 -> -0.21212121 | K76: 0.04 | L76: =G76-19% -> 0.38575758
B77: VALEMAX (0,05) A | D77: 22 | E77: 1 | F77: 15.5 | G77: =(D77-F77)/F77 -> 0.41935484 | H77: 20 | I77: =(H77-F77)/F77 -> 0.29032258 | J77: =G77-I77 -> 0.12903226 | K77: 0.04 | L77: =G77-19% -> 0.22935484
B78: Yara Vitta Bortrac (0,5) A | D78: 13.6 | E78: 1 | F78: 7.7 | G78: =(D78-F78)/F78 -> 0.76623377 | H78: 9.9 | I78: =(H78-F78)/F78 -> 0.28571429 | J78: =G78-I78 -> 0.48051948 | K78: 0.04 | L78: =G78-19% -> 0.57623377
B79: Yara Vitta Folicare (2 -4) A | D79: 5.95 | E79: 10 | F79: 3.5 | G79: =(D79-F79)/F79 -> 0.7 | H79: 5 | I79: =(H79-F79)/F79 -> 0.42857143 | J79: =G79-I79 -> 0.27142857 | K79: 0.04 | L79: =G79-19% -> 0.51
B80: Yara Vitta Glytrel (1) A | D80: 11.2 | E80: 10 | F80: 6 | G80: =(D80-F80)/F80 -> 0.86666667 | H80: 9 | I80: =(H80-F80)/F80 -> 0.5 | J80: =G80-I80 -> 0.36666667 | K80: 0.04 | L80: =G80-19% -> 0.67666667

Sheet Pacote
C3: Cliente | D3: APARECIDO | F3: Cant. Ha | G3: 120
F4: Sacas/Ha | G4: =IF(G16>0.1,G18,"ERRO") -> 7.6906074 | H4: Valor da Saca
F5: Contrato Kg | G5: =IF(G16>=0.1,ROUNDUP(G17*60,0),"ERRO") -> 55373
F6: Total USD | G6: =IF(AND(SUM(D23:D69)>=8,G71>=3),SUM(L23:L69),"ERRO") -> 21125 | H6: =G12 -> 23
F7: Contrato em Aberto Kg | G7: =+G5*1.3 -> 71984.9
G8: Disponivel
G9: Soja 23/24
F10: Total Custo | G10: =SUM(M24:M69) -> 15432.5
F11: Margem | G11: =(G6-G10)/G10 -> 0.36886441
F12: Preco da Soja | G12: 23 | H12: =IF(G11>=X14,X15,IF(G11>=W14,W15,IF(G11>=V14,V15,IF(G11>=U14,U15,IF(G11>=T14,T15,IF(G11>=S14,S15,IF(G11>=R14,R15,IF(G11>=Q14,Q15,IF(G11>=P14,P15,"ERRO"))))))))) -> 22
F13: Preço Livre | G13: =G12-(G12/21*10/100) -> 22.890476 | T13: Margem
F14: Precio real Soja | G14: 19.68 | P14: =P16+P17 -> 0.096 | Q14: =Q16+Q17 -> 0.1321 | R14: =R16+R17 -> 0.1437 | S14: =S16+S17 -> 0.1548 | T14: =T16+T17 -> 0.1664 | U14: =U16+U17 -> 0.1775 | V14: =V16+V17 -> 0.1891 | W14: =W16+W17 -> 0.2002 | X14: =X16+X17 -> 0.2118
F15: DIF Preco Real | G15: =(G12-G14)/G14 -> 0.16869919 | P15: 21 | Q15: 21.12 | R15: 21.25 | S15: 21.37 | T15: 21.5 | U15: 21.62 | V15: 21.75 | W15: 21.87 | X15: 22
F16: Margem | G16: =G11-G15 -> 0.20016522 | H16: =ROUND(G16,4) -> 0.2002 | P16: 0.066 | Q16: 0.0721 | R16: 0.0787 | S16: 0.0848 | T16: 0.0914 | U16: 0.0975 | V16: 0.1041 | W16: 0.1102 | X16: 0.1168
F17: Quantidade de Sacas | G17: =G6/G13 -> 922.87289 | H17: 0.1 | P17: 0.03 | Q17: 0.06 | R17: 0.065 | S17: 0.07 | T17: 0.075 | U17: 0.08 | V17: 0.085 | W17: 0.09 | X17: 0.095
F18: Sa/Ha | G18: =G17/G3 -> 7.6906074 | H18: =H16-H17 -> 0.1002
F19: Lucro Liq. | G19: =G10*G16 -> 3089.0498
O20: =SUM(O31:O69) -> 386.405
C21: ="V."&O20&"." -> V.386,405.
C23: Fert | D23: Aplic. | E23: Produto | F23: Dose/Ha (Kg/Ha) | G23: Cant. Produto | H23: Precio | I23: PREÇO | K23: QUAT. EXATA | L23: U$/AREA | M23: US Custo
C24: Fert | G24: =IF(E24="",0,MROUND(K24,VLOOKUP(E24,Precos!$B$2:$E$13,4,1))) -> 0 | H24: =I24 -> 0 | I24: =IF(E24="",0,VLOOKUP(E24,Precos!$B$2:$E$4,3,1)) -> 0 | J24: =IF(E24="",0,VLOOKUP(E24,Precos!$B$2:$G$4,5,1)) -> 0 | K24: =$G$3*D24*F24 -> 0 | L24: =G24*I24 -> 0 | M24: =G24*J24 -> 0 | N24: =IF(E24="",0,VLOOKUP(E24,Precos!$B$2:$K$4,10,1)) -> 0 | O24: =L24*N24 -> 0
C25: Fert | G25: =IF(E25="",0,MROUND(K25,VLOOKUP(E25,Precos!$B$2:$E$13,4,1))) -> 0 | H25: =I25 -> 0 | I25: =IF(E25="",0,VLOOKUP(E25,Precos!$B$2:$E$4,3,1)) -> 0 | J25: =IF(E25="",0,VLOOKUP(E25,Precos!$B$2:$G$4,5,1)) -> 0 | K25: =$G$3*D25*F25 -> 0 | L25: =G25*I25 -> 0 | M25: =G25*J25 -> 0 | N25: =IF(E25="",0,VLOOKUP(E25,Precos!$B$2:$K$4,10,1)) -> 0 | O25: =L25*N25 -> 0
C26: Fert | G26: =IF(E26="",0,MROUND(K26,VLOOKUP(E26,Precos!$B$2:$E$13,4,1))) -> 0 | H26: =I26 -> 0 | I26: =IF(E26="",0,VLOOKUP(E26,Precos!$B$2:$E$4,3,1)) -> 0 | J26: =IF(E26="",0,VLOOKUP(E26,Precos!$B$2:$G$4,5,1)) -> 0 | K26: =$G$3*D26*F26 -> 0 | L26: =G26*I26 -> 0 | M26: =G26*J26 -> 0 | N26: =IF(E26="",0,VLOOKUP(E26,Precos!$B$2:$K$4,10,1)) -> 0 | O26: =L26*N26 -> 0
C27: Fert | G27: =IF(E27="",0,MROUND(K27,VLOOKUP(E27,Precos!$B$2:$E$13,4,1))) -> 0 | H27: =I27 -> 0 | I27: =IF(E27="",0,VLOOKUP(E27,Precos!$B$2:$E$4,3,1)) -> 0 | J27: =IF(E27="",0,VLOOKUP(E27,Precos!$B$2:$G$4,5,1)) -> 0 | K27: =$G$3*D27*F27 -> 0 | L27: =G27*I27 -> 0 | M27: =G27*J27 -> 0 | N27: =IF(E27="",0,VLOOKUP(E27,Precos!$B$2:$K$4,10,1)) -> 0 | O27: =L27*N27 -> 0
C28: Fert | G28: =IF(E28="",0,MROUND(K28,VLOOKUP(E28,Precos!$B$2:$E$13,4,1))) -> 0 | H28: =I28 -> 0 | I28: =IF(E28="",0,VLOOKUP(E28,Precos!$B$2:$E$4,3,1)) -> 0 | J28: =IF(E28="",0,VLOOKUP(E28,Precos!$B$2:$G$4,5,1)) -> 0 | K28: =$G$3*D28*F28 -> 0 | L28: =G28*I28 -> 0 | M28: =G28*J28 -> 0 | N28: =IF(E28="",0,VLOOKUP(E28,Precos!$B$2:$K$4,10,1)) -> 0 | O28: =L28*N28 -> 0
C29: Fert | G29: =IF(E29="",0,MROUND(K29,VLOOKUP(E29,Precos!$B$2:$E$13,4,1))) -> 0 | H29: =I29 -> 0 | I29: =IF(E29="",0,VLOOKUP(E29,Precos!$B$2:$E$4,3,1)) -> 0 | J29: =IF(E29="",0,VLOOKUP(E29,Precos!$B$2:$G$4,5,1)) -> 0 | K29: =$G$3*D29*F29 -> 0 | L29: =G29*I29 -> 0 | M29: =G29*J29 -> 0 | N29: =IF(E29="",0,VLOOKUP(E29,Precos!$B$2:$K$4,10,1)) -> 0 | O29: =L29*N29 -> 0
C30: Semente | D30: Aplic. | E30: Produto | F30: Dose/Ha (sc de 125mil) | G30: Cant. Produto | H30: Precio | I30: PREÇO | K30: QUAT. EXATA | L30: U$/AREA | M30: US Custo
C31: Semente | D31: 1 | E31: 64IX66 RSF (NEXUS) (235mil/Há) A | G31: =IF(E31="",0,MROUND(K31,VLOOKUP(E31,Precos!$B$6:$E$23,4,1))) -> 0 | H31: =I31 -> 33 | I31: =IF(E31="",0,VLOOKUP(E31,Precos!$B$6:$E$23,3,1)) -> 33 | J31: =IF(E31="",0,VLOOKUP(E31,Precos!$B$6:$G$23,5,1)) -> 23.81 | K31: =$G$3*D31*F31 -> 0 | L31: =G31*I31 -> 0 | M31: =G31*J31 -> 0 | N31: =IF(E31="",0,VLOOKUP(E31,Precos!$B$6:$K$14,10,1)) -> 0.025 | O31: =L31*N31 -> 0
C32: Semente | G32: =IF(E32="",0,MROUND(K32,VLOOKUP(E32,Precos!$B$6:$E$23,4,1))) -> 0 | H32: =I32 -> 0 | I32: =IF(E32="",0,VLOOKUP(E32,Precos!$B$6:$E$23,3,1)) -> 0 | J32: =IF(E32="",0,VLOOKUP(E32,Precos!$B$6:$G$23,5,1)) -> 0 | K32: =$G$3*D32*F32 -> 0 | L32: =G32*I32 -> 0 | M32: =G32*J32 -> 0 | N32: =IF(E32="",0,VLOOKUP(E32,Precos!$B$6:$K$14,10,1)) -> 0 | O32: =L32*N32 -> 0
C33: Semente | G33: =IF(E33="",0,MROUND(K33,VLOOKUP(E33,Precos!$B$6:$E$23,4,1))) -> 0 | H33: =I33 -> 0 | I33: =IF(E33="",0,VLOOKUP(E33,Precos!$B$6:$E$23,3,1)) -> 0 | J33: =IF(E33="",0,VLOOKUP(E33,Precos!$B$6:$G$23,5,1)) -> 0 | K33: =$G$3*D33*F33 -> 0 | L33: =G33*I33 -> 0 | M33: =G33*J33 -> 0 | N33: =IF(E33="",0,VLOOKUP(E33,Precos!$B$6:$K$14,10,1)) -> 0 | O33: =L33*N33 -> 0
C34: Semente | G34: =IF(E34="",0,MROUND(K34,VLOOKUP(E34,Precos!$B$6:$E$23,4,1))) -> 0 | H34: =I34 -> 0 | I34: =IF(E34="",0,VLOOKUP(E34,Precos!$B$6:$E$23,3,1)) -> 0 | J34: =IF(E34="",0,VLOOKUP(E34,Precos!$B$6:$G$23,5,1)) -> 0 | K34: =$G$3*D34*F34 -> 0 | L34: =G34*I34 -> 0 | M34: =G34*J34 -> 0 | N34: =IF(E34="",0,VLOOKUP(E34,Precos!$B$6:$K$14,10,1)) -> 0 | O34: =L34*N34 -> 0
C35: TS | D35: Aplic. | E35: Produto | F35: Dose/Ha (Lt/Kg de sem.) | G35: Cant. Produto | H35: Precio | I35: PREÇO | K35: QUAT. EXATA | L35: U$/AREA | M35: US Custo
C36: TS | D36: 1 | E36: Clorante 62,5 (0,5 ml/Kg) A | F36: 0.03 | G36: =IF(E36="",0,MROUND(K36,VLOOKUP(E36,Precos!$B$25:$E$34,4,1))) -> 5 | H36: =I36 -> 90 | I36: =IF(E36="",0,VLOOKUP(E36,Precos!$B$25:$E$34,3,1)) -> 90 | J36: =IF(E36="",0,VLOOKUP(E36,Precos!$B$25:$G$34,5,1)) -> 60 | K36: =$G$3*D36*F36 -> 3.6 | L36: =G36*I36 -> 450 | M36: =G36*J36 -> 300 | N36: =IF(E36="",0,VLOOKUP(E36,Precos!B25:K34,10,1)) -> 0.01 | O36: =L36*N36 -> 4.5
C37: TS | D37: 1 | E37: Rancona (1 ml/kg) C | F37: 0.04 | G37: =IF(E37="",0,MROUND(K37,VLOOKUP(E37,Precos!$B$25:$E$34,4,1))) -> 5 | H37: =I37 -> 49.5 | I37: =IF(E37="",0,VLOOKUP(E37,Precos!$B$25:$E$34,3,1)) -> 49.5 | J37: =IF(E37="",0,VLOOKUP(E37,Precos!$B$25:$G$34,5,1)) -> 42 | K37: =$G$3*D37*F37 -> 4.8 | L37: =G37*I37 -> 247.5 | M37: =G37*J37 -> 210 | N37: =IF(E37="",0,VLOOKUP(E37,Precos!$B$25:$K$34,10,1)) -> 0.004 | O37: =L37*N37 -> 0.99
C38: TS | D38: 1 | E38: Fertactyl Leg (2 ml/kg) A | F38: 0.08 | G38: =IF(E38="",0,MROUND(K38,VLOOKUP(E38,Precos!$B$25:$E$34,4,1))) -> 10 | H38: =I38 -> 107 | I38: =IF(E38="",0,VLOOKUP(E38,Precos!$B$25:$E$34,3,1)) -> 107 | J38: =IF(E38="",0,VLOOKUP(E38,Precos!$B$25:$G$34,5,1)) -> 79 | K38: =$G$3*D38*F38 -> 9.6 | L38: =G38*I38 -> 1070 | M38: =G38*J38 -> 790 | N38: =IF(E38="",0,VLOOKUP(E38,Precos!$B$25:$K$34,10,1)) -> 0.04 | O38: =L38*N38 -> 42.8
C39: TS | D39: 1 | E39: Rizoliq Top (2 ml/kg) A | F39: 0.08 | G39: =IF(E39="",0,MROUND(K39,VLOOKUP(E39,Precos!$B$25:$E$34,4,1))) -> 10 | H39: =I39 -> 26 | I39: =IF(E39="",0,VLOOKUP(E39,Precos!$B$25:$E$34,3,1)) -> 26 | J39: =IF(E39="",0,VLOOKUP(E39,Precos!$B$25:$G$34,5,1)) -> 16 | K39: =$G$3*D39*F39 -> 9.6 | L39: =G39*I39 -> 260 | M39: =G39*J39 -> 160 | N39: =IF(E39="",0,VLOOKUP(E39,Precos!$B$25:$K$34,10,1)) -> 0.04 | O39: =L39*N39 -> 10.4
C40: TS | G40: =IF(E40="",0,MROUND(K40,VLOOKUP(E40,Precos!$B$25:$E$34,4,1))) -> 0 | H40: =I40 -> 0 | I40: =IF(E40="",0,VLOOKUP(E40,Precos!$B$25:$E$34,3,1)) -> 0 | J40: =IF(E40="",0,VLOOKUP(E40,Precos!$B$25:$G$34,5,1)) -> 0 | K40: =$G$3*D40*F40 -> 0 | L40: =G40*I40 -> 0 | M40: =G40*J40 -> 0 | N40: =IF(E40="",0,VLOOKUP(E40,Precos!$B$25:$K$34,10,1)) -> 0 | O40: =L40*N40 -> 0
C41: TS | G41: =IF(E41="",0,MROUND(K41,VLOOKUP(E41,Precos!$B$25:$E$34,4,1))) -> 0 | H41: =I41 -> 0 | I41: =IF(E41="",0,VLOOKUP(E41,Precos!$B$25:$E$34,3,1)) -> 0 | J41: =IF(E41="",0,VLOOKUP(E41,Precos!$B$25:$G$34,5,1)) -> 0 | K41: =$G$3*D41*F41 -> 0 | L41: =G41*I41 -> 0 | M41: =G41*J41 -> 0 | N41: =IF(E41="",0,VLOOKUP(E41,Precos!$B$25:$K$34,10,1)) -> 0 | O41: =L41*N41 -> 0
C42: HERBICIDAS | D42: Aplic. | E42: Produto | F42: Dose/Ha (Lt ou KgHa) | G42: Cant. Produto | H42: Precio | I42: PREÇO | K42: QUAT. EXATA | L42: U$/AREA | M42: US Custo
C43: HERBICIDAS | E43: Clomazone 48% (0,8 - 1) C | F43: 1 | G43: =IF(E43="",0,MROUND(K43,VLOOKUP(E43,Precos!$B$36:$E$43,4,1))) -> 0 | H43: =I43 -> 9.5 | I43: =IF(E43="",0,VLOOKUP(E43,Precos!$B$36:$E$44,3,1)) -> 9.5 | J43: =IF(E43="",0,VLOOKUP(E43,Precos!$B$36:G$44,5,1)) -> 7.5 | K43: =$G$3*D43*F43 -> 0 | L43: =G43*I43 -> 0 | M43: =G43*J43 -> 0 | N43: =IF(E43="",0,VLOOKUP(E43,Precos!$B$36:$K$42,10,1)) -> 0.004 | O43: =L43*N43 -> 0
C44: HERBICIDAS | D44: 1 | E44: Glufosinato 40 (1,5 – 2,5) C | F44: 1 | G44: =IF(E44="",0,MROUND(K44,VLOOKUP(E44,Precos!$B$36:$E$43,4,1))) -> 120 | H44: =I44 -> 6.1 | I44: =IF(E44="",0,VLOOKUP(E44,Precos!$B$36:$E$44,3,1)) -> 6.1 | J44: =IF(E44="",0,VLOOKUP(E44,Precos!$B$36:G$44,5,1)) -> 4.9 | K44: =$G$3*D44*F44 -> 120 | L44: =G44*I44 -> 732 | M44: =G44*J44 -> 588 | N44: =IF(E44="",0,VLOOKUP(E44,Precos!$B$36:$K$42,10,1)) -> 0.004 | O44: =L44*N44 -> 2.928
C45: HERBICIDAS | D45: 1 | E45: Verdict Ultra (0,08) C | F45: 0.08 | G45: =IF(E45="",0,MROUND(K45,VLOOKUP(E45,Precos!$B$36:$E$43,4,1))) -> 10 | H45: =I45 -> 88 | I45: =IF(E45="",0,VLOOKUP(E45,Precos!$B$36:$E$44,3,1)) -> 88 | J45: =IF(E45="",0,VLOOKUP(E45,Precos!$B$36:G$44,5,1)) -> 72 | K45: =$G$3*D45*F45 -> 9.6 | L45: =G45*I45 -> 880 | M45: =G45*J45 -> 720 | N45: =IF(E45="",0,VLOOKUP(E45,Precos!$B$36:$K$42,10,1)) -> 0.004 | O45: =L45*N45 -> 3.52
C46: HERBICIDAS | G46: =IF(E46="",0,MROUND(K46,VLOOKUP(E46,Precos!$B$36:$E$43,4,1))) -> 0 | H46: =I46 -> 0 | I46: =IF(E46="",0,VLOOKUP(E46,Precos!$B$36:$E$44,3,1)) -> 0 | J46: =IF(E46="",0,VLOOKUP(E46,Precos!$B$36:G$44,5,1)) -> 0 | K46: =$G$3*D46*F46 -> 0 | L46: =G46*I46 -> 0 | M46: =G46*J46 -> 0 | N46: =IF(E46="",0,VLOOKUP(E46,Precos!$B$36:$K$42,10,1)) -> 0 | O46: =L46*N46 -> 0
C47: HERBICIDAS | G47: =IF(E47="",0,MROUND(K47,VLOOKUP(E47,Precos!$B$36:$E$43,4,1))) -> 0 | H47: =I47 -> 0 | I47: =IF(E47="",0,VLOOKUP(E47,Precos!$B$36:$E$44,3,1)) -> 0 | J47: =IF(E47="",0,VLOOKUP(E47,Precos!$B$36:G$44,5,1)) -> 0 | K47: =$G$3*D47*F47 -> 0 | L47: =G47*I47 -> 0 | M47: =G47*J47 -> 0 | N47: =IF(E47="",0,VLOOKUP(E47,Precos!$B$36:$K$42,10,1)) -> 0 | O47: =L47*N47 -> 0
C48: HERBICIDAS | G48: =IF(E48="",0,MROUND(K48,VLOOKUP(E48,Precos!$B$36:$E$43,4,1))) -> 0 | H48: =I48 -> 0 | I48: =IF(E48="",0,VLOOKUP(E48,Precos!$B$36:$E$44,3,1)) -> 0 | J48: =IF(E48="",0,VLOOKUP(E48,Precos!$B$36:G$44,5,1)) -> 0 | K48: =$G$3*D48*F48 -> 0 | L48: =G48*I48 -> 0 | M48: =G48*J48 -> 0 | N48: =IF(E48="",0,VLOOKUP(E48,Precos!$B$36:$K$42,10,1)) -> 0 | O48: =L48*N48 -> 0
C49: INSETICIDAS | D49: Aplic. | E49: Produto | F49: Dose/Ha (Lt ou KgHa) | G49: Cant. Produto | H49: Precio | I49: PREÇO | K49: QUAT. EXATA | L49: U$/AREA | M49: US Custo
C50: INSETICIDAS | D50: 2 | E50: Toxatrin (0,3 - 0,5) A | F50: 0.4 | G50: =IF(E50="",0,MROUND(K50,VLOOKUP(E50,Precos!$B$45:$E$57,4,1))) -> 95 | H50: =I50 -> 19.5 | I50: =IF(E50="",0,VLOOKUP(E50,Precos!$B$45:$E$57,3,1)) -> 19.5 | J50: =IF(E50="",0,VLOOKUP(E50,Precos!$B$45:G$57,5,1)) -> 12.5 | K50: =$G$3*D50*F50 -> 96 | L50: =G50*I50 -> 1852.5 | M50: =G50*J50 -> 1187.5 | N50: =IF(E50="",0,VLOOKUP(E50,Precos!$B$45:$K$56,10,1)) -> 0.01 | O50: =L50*N50 -> 18.525
C51: INSETICIDAS | D51: 1 | E51: Loyer (0,4 - 0,5) A | F51: 0.5 | G51: =IF(E51="",0,MROUND(K51,VLOOKUP(E51,Precos!$B$45:$E$57,4,1))) -> 60 | H51: =I51 -> 19.8 | I51: =IF(E51="",0,VLOOKUP(E51,Precos!$B$45:$E$57,3,1)) -> 19.8 | J51: =IF(E51="",0,VLOOKUP(E51,Precos!$B$45:G$57,5,1)) -> 14.5 | K51: =$G$3*D51*F51 -> 60 | L51: =G51*I51 -> 1188 | M51: =G51*J51 -> 870 | N51: =IF(E51="",0,VLOOKUP(E51,Precos!$B$45:$K$56,10,1)) -> 0.01 | O51: =L51*N51 -> 11.88
C52: INSETICIDAS | D52: 2 | E52: Clorante 80% (0,04) C | F52: 0.06 | G52: =IF(E52="",0,MROUND(K52,VLOOKUP(E52,Precos!$B$45:$E$57,4,1))) -> 14 | H52: =I52 -> 90 | I52: =IF(E52="",0,VLOOKUP(E52,Precos!$B$45:$E$57,3,1)) -> 90 | J52: =IF(E52="",0,VLOOKUP(E52,Precos!$B$45:G$57,5,1)) -> 70 | K52: =$G$3*D52*F52 -> 14.4 | L52: =G52*I52 -> 1260 | M52: =G52*J52 -> 980 | N52: =IF(E52="",0,VLOOKUP(E52,Precos!$B$45:$K$56,10,1)) -> 0.004 | O52: =L52*N52 -> 5.04
C53: INSETICIDAS | D53: 1 | E53: Lascar (0,8 – 1,0) B | F53: 1 | G53: =IF(E53="",0,MROUND(K53,VLOOKUP(E53,Precos!$B$45:$E$57,4,1))) -> 120 | H53: =I53 -> 11.8 | I53: =IF(E53="",0,VLOOKUP(E53,Precos!$B$45:$E$57,3,1)) -> 11.8 | J53: =IF(E53="",0,VLOOKUP(E53,Precos!$B$45:G$57,5,1)) -> 9 | K53: =$G$3*D53*F53 -> 120 | L53: =G53*I53 -> 1416 | M53: =G53*J53 -> 1080 | N53: =IF(E53="",0,VLOOKUP(E53,Precos!$B$45:$K$56,10,1)) -> 0.007 | O53: =L53*N53 -> 9.912
C54: INSETICIDAS | G54: =IF(E54="",0,MROUND(K54,VLOOKUP(E54,Precos!$B$45:$E$57,4,1))) -> 0 | H54: =I54 -> 0 | I54: =IF(E54="",0,VLOOKUP(E54,Precos!$B$45:$E$57,3,1)) -> 0 | J54: =IF(E54="",0,VLOOKUP(E54,Precos!$B$45:G$57,5,1)) -> 0 | K54: =$G$3*D54*F54 -> 0 | L54: =G54*I54 -> 0 | M54: =G54*J54 -> 0 | N54: =IF(E54="",0,VLOOKUP(E54,Precos!$B$45:$K$56,10,1)) -> 0 | O54: =L54*N54 -> 0
C55: INSETICIDAS | G55: =IF(E55="",0,MROUND(K55,VLOOKUP(E55,Precos!$B$45:$E$57,4,1))) -> 0 | H55: =I55 -> 0 | I55: =IF(E55="",0,VLOOKUP(E55,Precos!$B$45:$E$57,3,1)) -> 0 | J55: =IF(E55="",0,VLOOKUP(E55,Precos!$B$45:G$57,5,1)) -> 0 | K55: =$G$3*D55*F55 -> 0 | L55: =G55*I55 -> 0 | M55: =G55*J55 -> 0 | N55: =IF(E55="",0,VLOOKUP(E55,Precos!$B$45:$K$56,10,1)) -> 0 | O55: =L55*N55 -> 0
C56: FUNGICIDAS | D56: Aplic. | E56: Produto | F56: Dose/Ha (Lt ou KgHa) | G56: Cant. Produto | H56: Precio | I56: PREÇO | K56: QUAT. EXATA | L56: U$/AREA | M56: US Custo
C57: FUNGICIDAS | D57: 1 | E57: Difenazol (0,5) A | F57: 0.5 | G57: =IF(E57="",0,MROUND(K57,VLOOKUP(E57,Precos!$B$58:$E$66,4,1))) -> 60 | H57: =I57 -> 17.5 | I57: =IF(E57="",0,VLOOKUP(E57,Precos!$B$58:$E$66,3,1)) -> 17.5 | J57: =IF(E57="",0,VLOOKUP(E57,Precos!$B$58:$G$66,5,1)) -> 8.5 | K57: =$G$3*D57*F57 -> 60 | L57: =G57*I57 -> 1050 | M57: =G57*J57 -> 510 | N57: =IF(E57="",0,VLOOKUP(E57,Precos!$B$58:$K$66,10,1)) -> 0.01 | O57: =L57*N57 -> 10.5
C58: FUNGICIDAS | D58: 1 | E58: Viovan (0,6) B | F58: 0.5 | G58: =IF(E58="",0,MROUND(K58,VLOOKUP(E58,Precos!$B$58:$E$66,4,1))) -> 60 | H58: =I58 -> 40 | I58: =IF(E58="",0,VLOOKUP(E58,Precos!$B$58:$E$66,3,1)) -> 40 | J58: =IF(E58="",0,VLOOKUP(E58,Precos!$B$58:$G$66,5,1)) -> 31 | K58: =$G$3*D58*F58 -> 60 | L58: =G58*I58 -> 2400 | M58: =G58*J58 -> 1860 | N58: =IF(E58="",0,VLOOKUP(E58,Precos!$B$58:$K$66,10,1)) -> 0.007 | O58: =L58*N58 -> 16.8
C59: FUNGICIDAS | D59: 1 | E59: Vessaria (0,6) B | F59: 0.5 | G59: =IF(E59="",0,MROUND(K59,VLOOKUP(E59,Precos!$B$58:$E$66,4,1))) -> 60 | H59: =I59 -> 42.5 | I59: =IF(E59="",0,VLOOKUP(E59,Precos!$B$58:$E$66,3,1)) -> 42.5 | J59: =IF(E59="",0,VLOOKUP(E59,Precos!$B$58:$G$66,5,1)) -> 36.5 | K59: =$G$3*D59*F59 -> 60 | L59: =G59*I59 -> 2550 | M59: =G59*J59 -> 2190 | N59: =IF(E59="",0,VLOOKUP(E59,Precos!$B$58:$K$66,10,1)) -> 0.007 | O59: =L59*N59 -> 17.85
C60: FUNGICIDAS | G60: =IF(E60="",0,MROUND(K60,VLOOKUP(E60,Precos!$B$58:$E$66,4,1))) -> 0 | H60: =I60 -> 0 | I60: =IF(E60="",0,VLOOKUP(E60,Precos!$B$58:$E$66,3,1)) -> 0 | J60: =IF(E60="",0,VLOOKUP(E60,Precos!$B$58:$G$66,5,1)) -> 0 | K60: =$G$3*D60*F60 -> 0 | L60: =G60*I60 -> 0 | M60: =G60*J60 -> 0 | N60: =IF(E60="",0,VLOOKUP(E60,Precos!$B$58:$K$66,10,1)) -> 0 | O60: =L60*N60 -> 0
C61: FUNGICIDAS | G61: =IF(E61="",0,MROUND(K61,VLOOKUP(E61,Precos!$B$58:$E$66,4,1))) -> 0 | H61: =I61 -> 0 | I61: =IF(E61="",0,VLOOKUP(E61,Precos!$B$58:$E$66,3,1)) -> 0 | J61: =IF(E61="",0,VLOOKUP(E61,Precos!$B$58:$G$66,5,1)) -> 0 | K61: =$G$3*D61*F61 -> 0 | L61: =G61*I61 -> 0 | M61: =G61*J61 -> 0 | N61: =IF(E61="",0,VLOOKUP(E61,Precos!$B$58:$K$66,10,1)) -> 0 | O61: =L61*N61 -> 0
C62: FUNGICIDAS | G62: =IF(E62="",0,MROUND(K62,VLOOKUP(E62,Precos!$B$58:$E$66,4,1))) -> 0 | H62: =I62 -> 0 | I62: =IF(E62="",0,VLOOKUP(E62,Precos!$B$58:$E$66,3,1)) -> 0 | J62: =IF(E62="",0,VLOOKUP(E62,Precos!$B$58:$G$66,5,1)) -> 0 | K62: =$G$3*D62*F62 -> 0 | L62: =G62*I62 -> 0 | M62: =G62*J62 -> 0 | N62: =IF(E62="",0,VLOOKUP(E62,Precos!$B$58:$K$66,10,1)) -> 0 | O62: =L62*N62 -> 0
C63: ESPECIALIDADES | D63: Aplic. | E63: Produto | F63: Dose/Ha (Lt ou KgHa) | G63: Cant. Produto | H63: Precio | I63: PREÇO | K63: QUAT. EXATA | L63: U$/AREA | M63: US Custo
C64: ESPECIALIDADES | D64: 1 | E64: Progen Detox (0,4) A | F64: 0.5 | G64: =IF(E64="",0,MROUND(K64,VLOOKUP(E64,Precos!$B$68:$E$80,4,1))) -> 60 | H64: =I64 -> 31.85 | I64: =IF(E64="",0,VLOOKUP(E64,Precos!$B$68:$E$80,3,1)) -> 31.85 | J64: =IF(E64="",0,VLOOKUP(E64,Precos!$B$68:$G$80,5,1)) -> 22.8 | K64: =$G$3*D64*F64 -> 60 | L64: =G64*I64 -> 1911 | M64: =G64*J64 -> 1368 | N64: =IF(E64="",0,VLOOKUP(E64,Precos!$B$68:$K$80,10,1)) -> 0.04 | O64: =L64*N64 -> 76.44
C65: ESPECIALIDADES | D65: 1 | E65: Fertileader Vital 954 (1) A | F65: 1 | G65: =IF(E65="",0,MROUND(K65,VLOOKUP(E65,Precos!$B$68:$E$80,4,1))) -> 120 | H65: =I65 -> 28.85 | I65: =IF(E65="",0,VLOOKUP(E65,Precos!$B$68:$E$80,3,1)) -> 28.85 | J65: =IF(E65="",0,VLOOKUP(E65,Precos!$B$68:$G$80,5,1)) -> 19.5 | K65: =$G$3*D65*F65 -> 120 | L65: =G65*I65 -> 3462 | M65: =G65*J65 -> 2340 | N65: =IF(E65="",0,VLOOKUP(E65,Precos!$B$68:$K$80,10,1)) -> 0.04 | O65: =L65*N65 -> 138.48
C66: ESPECIALIDADES | D66: 3 | E66: VALEMAX (0,05) A | F66: 0.05 | G66: =IF(E66="",0,MROUND(K66,VLOOKUP(E66,Precos!$B$68:$E$80,4,1))) -> 18 | H66: =I66 -> 22 | I66: =IF(E66="",0,VLOOKUP(E66,Precos!$B$68:$E$80,3,1)) -> 22 | J66: =IF(E66="",0,VLOOKUP(E66,Precos!$B$68:$G$80,5,1)) -> 15.5 | K66: =$G$3*D66*F66 -> 18 | L66: =G66*I66 -> 396 | M66: =G66*J66 -> 279 | N66: =IF(E66="",0,VLOOKUP(E66,Precos!$B$68:$K$80,10,1)) -> 0.04 | O66: =L66*N66 -> 15.84
C67: ESPECIALIDADES | G67: =IF(E67="",0,MROUND(K67,VLOOKUP(E67,Precos!$B$68:$E$80,4,1))) -> 0 | H67: =I67 -> 0 | I67: =IF(E67="",0,VLOOKUP(E67,Precos!$B$68:$E$80,3,1)) -> 0 | J67: =IF(E67="",0,VLOOKUP(E67,Precos!$B$68:$G$80,5,1)) -> 0 | K67: =$G$3*D67*F67 -> 0 | L67: =G67*I67 -> 0 | M67: =G67*J67 -> 0 | N67: =IF(E67="",0,VLOOKUP(E67,Precos!$B$68:$K$80,10,1)) -> 0 | O67: =L67*N67 -> 0
C68: ESPECIALIDADES | G68: =IF(E68="",0,MROUND(K68,VLOOKUP(E68,Precos!$B$68:$E$80,4,1))) -> 0 | H68: =I68 -> 0 | I68: =IF(E68="",0,VLOOKUP(E68,Precos!$B$68:$E$80,3,1)) -> 0 | J68: =IF(E68="",0,VLOOKUP(E68,Precos!$B$68:$G$80,5,1)) -> 0 | K68: =$G$3*D68*F68 -> 0 | L68: =G68*I68 -> 0 | M68: =G68*J68 -> 0 | N68: =IF(E68="",0,VLOOKUP(E68,Precos!$B$68:$K$80,10,1)) -> 0 | O68: =L68*N68 -> 0
C69: ESPECIALIDADES | G69: =IF(E69="",0,MROUND(K69,VLOOKUP(E69,Precos!$B$68:$E$80,4,1))) -> 0 | H69: =I69 -> 0 | I69: =IF(E69="",0,VLOOKUP(E69,Precos!$B$68:$E$80,3,1)) -> 0 | J69: =IF(E69="",0,VLOOKUP(E69,Precos!$B$68:$G$80,5,1)) -> 0 | K69: =$G$3*D69*F69 -> 0 | L69: =G69*I69 -> 0 | M69: =G69*J69 -> 0 | N69: =IF(E69="",0,VLOOKUP(E69,Precos!$B$68:$K$80,10,1)) -> 0 | O69: =L69*N69 -> 0
G71: =COUNTIF($G$64:$G$69,">0") -> 3
